pyccea/__init__.py
pyccea/coevolution/README.md
pyccea/coevolution/__init__.py
pyccea/coevolution/ccea.py
pyccea/coevolution/cceafs.py
pyccea/coevolution/ccfc.py
pyccea/coevolution/ccfsrfg1.py
pyccea/coevolution/ccfsrfg2.py
pyccea/coevolution/ccga.py
pyccea/coevolution/ccilfg.py
pyccea/coevolution/ccpstfg.py
pyccea/coevolution/ccsufg.py
pyccea/cooperation/__init__.py
pyccea/cooperation/best.py
pyccea/cooperation/collaboration.py
pyccea/cooperation/elite.py
pyccea/cooperation/random.py
pyccea/datasets/11_tumor.parquet
pyccea/datasets/9_tumor.parquet
pyccea/datasets/brain_tumor_1.parquet
pyccea/datasets/brain_tumor_2.parquet
pyccea/datasets/cbd.parquet
pyccea/datasets/dermatology.parquet
pyccea/datasets/divorce.parquet
pyccea/datasets/dlbcl.parquet
pyccea/datasets/dorothea.parquet
pyccea/datasets/gfe.parquet
pyccea/datasets/hapt.parquet
pyccea/datasets/har.parquet
pyccea/datasets/isolet5.parquet
pyccea/datasets/itt_f.parquet
pyccea/datasets/itt_m.parquet
pyccea/datasets/leukemia_1.parquet
pyccea/datasets/leukemia_2.parquet
pyccea/datasets/leukemia_3.parquet
pyccea/datasets/libras.parquet
pyccea/datasets/lsvt.parquet
pyccea/datasets/lungc.parquet
pyccea/datasets/madelon_valid.parquet
pyccea/datasets/mfd.parquet
pyccea/datasets/orh.parquet
pyccea/datasets/prostate_tumor_1.parquet
pyccea/datasets/qsar_oral_toxicity.parquet
pyccea/datasets/scadi.parquet
pyccea/datasets/shd.parquet
pyccea/datasets/uji_indoor_loc.parquet
pyccea/datasets/wdbc.parquet
pyccea/decomposition/README.md
pyccea/decomposition/__init__.py
pyccea/decomposition/clustering.py
pyccea/decomposition/dummy.py
pyccea/decomposition/grouping.py
pyccea/decomposition/random.py
pyccea/decomposition/ranking.py
pyccea/decomposition/static.py
pyccea/evaluation/__init__.py
pyccea/evaluation/wrapper.py
pyccea/fitness/__init__.py
pyccea/fitness/distance.py
pyccea/fitness/function.py
pyccea/fitness/penalty.py
pyccea/initialization/__init__.py
pyccea/initialization/binary.py
pyccea/initialization/build.py
pyccea-1.0.2.dist-info/LICENSE
pyccea-1.0.2.dist-info/METADATA
pyccea-1.0.2.dist-info/WHEEL
pyccea-1.0.2.dist-info/RECORD
