Metadata-Version: 2.3
Name: pyccea
Version: 1.0.2
Summary: Cooperative co-evolutionary algorithms for feature selection in high-dimensional data
License: MIT
Author: Pedro Vinícius A. B. Venâncio
Author-email: pedbrgs@gmail.com
Requires-Python: >=3.10
Classifier: License :: OSI Approved :: MIT License
Classifier: Programming Language :: Python :: 3
Classifier: Programming Language :: Python :: 3.10
Classifier: Programming Language :: Python :: 3.11
Classifier: Programming Language :: Python :: 3.12
Classifier: Programming Language :: Python :: 3.13
Requires-Dist: fsspec (==2025.5.1)
Requires-Dist: imbalanced-learn (==0.13.0)
Requires-Dist: kneed (==0.8.5)
Requires-Dist: numpy (==2.2.0)
Requires-Dist: pandas (==2.2.3)
Requires-Dist: pyarrow (==20.0.0)
Requires-Dist: scikit-learn (==1.6.1)
Requires-Dist: scipy (==1.15.3)
Requires-Dist: toml (==0.10.2)
Requires-Dist: tqdm (==4.65.0)
Requires-Dist: tqdm-joblib (==0.0.4)
Project-URL: Homepage, https://github.com/pedbrgs/PyCCEA
